helloml/__init__.py
helloml/template.py
helloml-0.0.2.dist-info/LICENSE
helloml-0.0.2.dist-info/METADATA
helloml-0.0.2.dist-info/WHEEL
helloml-0.0.2.dist-info/top_level.txt
helloml-0.0.2.dist-info/RECORD
