Metadata-Version: 2.1
Name: helloml
Version: 0.0.2
Summary: A package of machine learning templates
Home-page: https://github.com/tanchihpin0517/helloml
Author: Chih-Pin Tan
Author-email: tanchihpin0517@gmail.com
License: UNKNOWN
Project-URL: Bug Tracker, https://github.com/tanchihpin0517/helloml/issues
Platform: UNKNOWN
Classifier: Programming Language :: Python :: 3
Classifier: License :: OSI Approved :: MIT License
Classifier: Operating System :: OS Independent
Requires-Python: >=3.8
License-File: LICENSE
